{"_id":"nodemailer-wellknown","_rev":"6-05fcbf5bc00f0ec85426e1568d895e5b","name":"nodemailer-wellknown","description":"Well known SMTP services","dist-tags":{"latest":"0.1.2"},"versions":{"0.1.0":{"name":"nodemailer-wellknown","version":"0.1.0","description":"Well known SMTP services","main":"index.js","scripts":{"test":"nodeunit test.js"},"repository":{"type":"git","url":"git://github.com/andris9/nodemailer-wellknown.git"},"keywords":["SMTP","Nodemailer"],"author":{"name":"Andris Reinman"},"license":"MIT","bugs":{"url":"https://github.com/andris9/nodemailer-wellknown/issues"},"homepage":"https://github.com/andris9/nodemailer-wellknown","devDependencies":{"nodeunit":"^0.9.0"},"_id":"nodemailer-wellknown@0.1.0","dist":{"shasum":"6b51ed82883f1b3086fa2f49767e87dfa0cdf35d","tarball":"http://registry.npmjs.org/nodemailer-wellknown/-/nodemailer-wellknown-0.1.0.tgz"},"_from":".","_npmVersion":"1.4.3","_npmUser":{"name":"andris","email":"andris@node.ee"},"maintainers":[{"name":"andris","email":"andris@node.ee"}],"directories":{}},"0.1.1":{"name":"nodemailer-wellknown","version":"0.1.1","description":"Well known SMTP services","main":"index.js","scripts":{"test":"nodeunit test.js"},"repository":{"type":"git","url":"git://github.com/andris9/nodemailer-wellknown.git"},"keywords":["SMTP","Nodemailer"],"author":{"name":"Andris Reinman"},"license":"MIT","bugs":{"url":"https://github.com/andris9/nodemailer-wellknown/issues"},"homepage":"https://github.com/andris9/nodemailer-wellknown","devDependencies":{"nodeunit":"^0.9.0"},"gitHead":"48680b451789708b3c9522abb82419136c09d688","_id":"nodemailer-wellknown@0.1.1","_shasum":"3cc2da64f38d89bd6b8432c3a938dde6a6a49a31","_from":".","_npmVersion":"1.4.14","_npmUser":{"name":"andris","email":"andris@node.ee"},"maintainers":[{"name":"andris","email":"andris@node.ee"}],"dist":{"shasum":"3cc2da64f38d89bd6b8432c3a938dde6a6a49a31","tarball":"http://registry.npmjs.org/nodemailer-wellknown/-/nodemailer-wellknown-0.1.1.tgz"},"directories":{}},"0.1.2":{"name":"nodemailer-wellknown","version":"0.1.2","description":"Well known SMTP services","main":"index.js","scripts":{"test":"nodeunit test.js"},"repository":{"type":"git","url":"git://github.com/andris9/nodemailer-wellknown.git"},"keywords":["SMTP","Nodemailer"],"author":{"name":"Andris Reinman"},"license":"MIT","bugs":{"url":"https://github.com/andris9/nodemailer-wellknown/issues"},"homepage":"https://github.com/andris9/nodemailer-wellknown","devDependencies":{"nodeunit":"^0.9.0"},"gitHead":"d6f6f985ca018b252c3054df9b1d08efdd3013e0","_id":"nodemailer-wellknown@0.1.2","_shasum":"f1f1c4369c6c845f287c162b4ec539bc019a9efc","_from":".","_npmVersion":"1.4.14","_npmUser":{"name":"andris","email":"andris@node.ee"},"maintainers":[{"name":"andris","email":"andris@node.ee"}],"dist":{"shasum":"f1f1c4369c6c845f287c162b4ec539bc019a9efc","tarball":"http://registry.npmjs.org/nodemailer-wellknown/-/nodemailer-wellknown-0.1.2.tgz"},"directories":{}}},"readme":"# Nodemailer Well-Known Services\n\nReturns SMTP configuration for well-known services\n\n## Usage\n\nInstall with npm\n\n    npm install nodemailer-wellknown\n\nRequire in your script\n\n```javascript\nvar wellknown = require('nodemailer-wellknown');\n```\n\nResolve SMTP settings\n\n```javascript\nvar config = wellknown('Gmail');\n// { host: 'smtp.gmail.com',\n//   port: 465,\n//   secure: true }\n```\n\n## Supported services\n\nService names are case insensitive\n\n  * **'1und1'**\n  * **'AOL'**\n  * **'DynectEmail'**\n  * **'FastMail'**\n  * **'Gmail'**\n  * **'Godaddy'**\n  * **'GodaddyAsia'**\n  * **'GodaddyEurope'**\n  * **'hot.ee'**\n  * **'Hotmail'**\n  * **'iCloud'**\n  * **'mail.ee'**\n  * **'Mail.ru'**\n  * **'Mailgun'**\n  * **'Mailjet'**\n  * **'Mandrill'**\n  * **'Postmark'**\n  * **'QQ'**\n  * **'QQex'**\n  * **'SendCloud'**\n  * **'SendGrid'**\n  * **'SES'**\n  * **'Yahoo'**\n  * **'Yandex'**\n  * **'Zoho'**\n\n### Example usage with Nodemailer\n\n> **NB!** This repo might be updated more often than Nodemailer itself, so in case\n> a wellknown host is not working, check that you have the latest version of\n> nodemailer-wellknown installed in your node_modules. Otherwise the data you try\n> to use might be still missing.\n\n```javascript\nvar transporter = nodemailer.createTransport({\n     service: 'postmark' // <- resolved as 'Postmark' from the wellknown info\n     auth: {...}\n});\n```\n\n## License\n\n**MIT**","maintainers":[{"name":"andris","email":"andris@node.ee"}],"time":{"modified":"2014-07-23T10:00:07.562Z","created":"2014-06-24T21:20:25.417Z","0.1.0":"2014-06-24T21:20:25.417Z","0.1.1":"2014-07-16T08:02:15.779Z","0.1.2":"2014-07-23T10:00:07.562Z"},"homepage":"https://github.com/andris9/nodemailer-wellknown","keywords":["SMTP","Nodemailer"],"repository":{"type":"git","url":"git://github.com/andris9/nodemailer-wellknown.git"},"author":{"name":"Andris Reinman"},"bugs":{"url":"https://github.com/andris9/nodemailer-wellknown/issues"},"license":"MIT","readmeFilename":"README.md","_attachments":{},"_etag":"\"2T7YY5R4RAJQEQUXOVUAXRT1S\""}